MANIFEST.in
setup.py
docroot/etc/init.d/netconns
netkraken/__init__.py
netkraken/db.py
netkraken_minion.egg-info/PKG-INFO
netkraken_minion.egg-info/SOURCES.txt
netkraken_minion.egg-info/dependency_links.txt
netkraken_minion.egg-info/requires.txt
netkraken_minion.egg-info/top_level.txt
netkraken_minion.egg-info/zip-safe
scripts/collect-netconns
scripts/netconns