Metadata-Version: 1.1
Name: netkraken-minion
Version: 0.2
Summary: records network connections: source host, protocol, target host
Home-page: https://github.com/netkraken/minion
Author: Arne Hilmann
Author-email: arne.hilmann@gmail.com
License: UNKNOWN
Platform: UNKNOWN
Classifier: Development Status :: 3 - Alpha
Classifier: Programming Language :: Python
